bibiso4/__init__.py
bibiso4/exact.json
bibiso4/prefix.json
bibiso4/suffix.json
bibiso4-1.0.1.dist-info/licenses/LICENSE
bibiso4-1.0.1.dist-info/METADATA
bibiso4-1.0.1.dist-info/WHEEL
bibiso4-1.0.1.dist-info/entry_points.txt
bibiso4-1.0.1.dist-info/top_level.txt
bibiso4-1.0.1.dist-info/RECORD
