Metadata-Version: 2.4
Name: bibiso4
Version: 1.0.1
Author-email: Andrew Fowlie <andrew.j.fowlie@gmail.com>
Classifier: Programming Language :: Python :: 3
Classifier: License :: OSI Approved :: MIT License
Classifier: Operating System :: OS Independent
Requires-Python: >=3.8
License-File: LICENSE
Dynamic: license-file
